{ "_id" : { "$oid" : "5924f685cefd3225c313116b" }, "user" : "0001", "count1" : "1", "date1" : "01/02/2017", "type1" : "Sick Leave", "note1" : "Sick", "count2" : "2", "date2" : "02/02/2017", "type2" : "Holiday leave", "note2" : "", "count3" : "3", "date3" : "03/02/2017", "type3" : "Sick Leave", "note3" : "Headache", "count4" : "4", "date4" : "04/02/2017", "type4" : "Errand leave", "note4" : "Meeting", "count5" : "5", "date5" : "05/02/2017", "type5" : "Holiday leave", "note5" : "" }
{ "_id" : { "$oid" : "592504b5cefd3225c313116c" }, "user" : "0002", "count1" : "1", "date1" : "01/02/2017", "type1" : "Sick Leave", "note1" : "Sick", "count2" : "2", "date2" : "02/02/2017", "type2" : "Holiday leave", "note2" : "", "count3" : "3", "date3" : "03/02/2017", "type3" : "Sick Leave", "note3" : "Headache" }
{ "_id" : { "$oid" : "59250be21fad113860c225cd" }, "count6" : "6", "date6" : "2017-05-13", "type6" : "sdfbkj", "note6" : "SDV;IJ" }
